Compiled from "Customer.java"
class rentalStore.Customer {
  private java.lang.String _name;

  private java.util.Vector<rentalStore.Rental> _rentals;

  public rentalStore.Customer(java.lang.String);
    Code:
       0: aload_0       
       1: invokespecial #14                 // Method java/lang/Object."<init>":()V
       4: aload_0       
       5: new           #17                 // class java/util/Vector
       8: dup           
       9: invokespecial #19                 // Method java/util/Vector."<init>":()V
      12: putfield      #20                 // Field _rentals:Ljava/util/Vector;
      15: aload_0       
      16: aload_1       
      17: putfield      #22                 // Field _name:Ljava/lang/String;
      20: return        

  public void addRental(rentalStore.Rental);
    Code:
       0: aload_0       
       1: getfield      #20                 // Field _rentals:Ljava/util/Vector;
       4: aload_1       
       5: invokevirtual #31                 // Method java/util/Vector.addElement:(Ljava/lang/Object;)V
       8: return        

  public java.lang.String getName();
    Code:
       0: aload_0       
       1: getfield      #22                 // Field _name:Ljava/lang/String;
       4: areturn       

  public java.lang.String statement();
    Code:
       0: aload_0       
       1: getfield      #20                 // Field _rentals:Ljava/util/Vector;
       4: invokevirtual #40                 // Method java/util/Vector.elements:()Ljava/util/Enumeration;
       7: astore_1      
       8: new           #44                 // class java/lang/StringBuilder
      11: dup           
      12: ldc           #46                 // String Rental Record for 
      14: invokespecial #48                 // Method java/lang/StringBuilder."<init>":(Ljava/lang/String;)V
      17: aload_0       
      18: invokevirtual #50                 // Method getName:()Ljava/lang/String;
      21: invokevirtual #52                 // Method java/lang/StringBuilder.append:(Ljava/lang/String;)Ljava/lang/StringBuilder;
      24: ldc           #56                 // String \n
      26: invokevirtual #52                 // Method java/lang/StringBuilder.append:(Ljava/lang/String;)Ljava/lang/StringBuilder;
      29: invokevirtual #58                 // Method java/lang/StringBuilder.toString:()Ljava/lang/String;
      32: astore_2      
      33: goto          96
      36: aload_1       
      37: invokeinterface #61,  1           // InterfaceMethod java/util/Enumeration.nextElement:()Ljava/lang/Object;
      42: checkcast     #67                 // class rentalStore/Rental
      45: astore_3      
      46: new           #44                 // class java/lang/StringBuilder
      49: dup           
      50: aload_2       
      51: invokestatic  #69                 // Method java/lang/String.valueOf:(Ljava/lang/Object;)Ljava/lang/String;
      54: invokespecial #48                 // Method java/lang/StringBuilder."<init>":(Ljava/lang/String;)V
      57: ldc           #75                 // String \t
      59: invokevirtual #52                 // Method java/lang/StringBuilder.append:(Ljava/lang/String;)Ljava/lang/StringBuilder;
      62: aload_3       
      63: invokevirtual #77                 // Method rentalStore/Rental.getMovie:()LrentalStore/Movie;
      66: invokevirtual #81                 // Method rentalStore/Movie.getTitle:()Ljava/lang/String;
      69: invokevirtual #52                 // Method java/lang/StringBuilder.append:(Ljava/lang/String;)Ljava/lang/StringBuilder;
      72: ldc           #75                 // String \t
      74: invokevirtual #52                 // Method java/lang/StringBuilder.append:(Ljava/lang/String;)Ljava/lang/StringBuilder;
      77: aload_3       
      78: invokevirtual #86                 // Method rentalStore/Rental.getCharge:()D
      81: invokestatic  #90                 // Method java/lang/String.valueOf:(D)Ljava/lang/String;
      84: invokevirtual #52                 // Method java/lang/StringBuilder.append:(Ljava/lang/String;)Ljava/lang/StringBuilder;
      87: ldc           #56                 // String \n
      89: invokevirtual #52                 // Method java/lang/StringBuilder.append:(Ljava/lang/String;)Ljava/lang/StringBuilder;
      92: invokevirtual #58                 // Method java/lang/StringBuilder.toString:()Ljava/lang/String;
      95: astore_2      
      96: aload_1       
      97: invokeinterface #93,  1           // InterfaceMethod java/util/Enumeration.hasMoreElements:()Z
     102: ifne          36
     105: new           #44                 // class java/lang/StringBuilder
     108: dup           
     109: aload_2       
     110: invokestatic  #69                 // Method java/lang/String.valueOf:(Ljava/lang/Object;)Ljava/lang/String;
     113: invokespecial #48                 // Method java/lang/StringBuilder."<init>":(Ljava/lang/String;)V
     116: ldc           #97                 // String Amount owed is 
     118: invokevirtual #52                 // Method java/lang/StringBuilder.append:(Ljava/lang/String;)Ljava/lang/StringBuilder;
     121: aload_0       
     122: invokespecial #99                 // Method getTotalCharge:()D
     125: invokestatic  #90                 // Method java/lang/String.valueOf:(D)Ljava/lang/String;
     128: invokevirtual #52                 // Method java/lang/StringBuilder.append:(Ljava/lang/String;)Ljava/lang/StringBuilder;
     131: ldc           #56                 // String \n
     133: invokevirtual #52                 // Method java/lang/StringBuilder.append:(Ljava/lang/String;)Ljava/lang/StringBuilder;
     136: invokevirtual #58                 // Method java/lang/StringBuilder.toString:()Ljava/lang/String;
     139: astore_2      
     140: new           #44                 // class java/lang/StringBuilder
     143: dup           
     144: aload_2       
     145: invokestatic  #69                 // Method java/lang/String.valueOf:(Ljava/lang/Object;)Ljava/lang/String;
     148: invokespecial #48                 // Method java/lang/StringBuilder."<init>":(Ljava/lang/String;)V
     151: ldc           #102                // String You earned 
     153: invokevirtual #52                 // Method java/lang/StringBuilder.append:(Ljava/lang/String;)Ljava/lang/StringBuilder;
     156: aload_0       
     157: invokespecial #104                // Method getTotalFrequentRenterPoints:()I
     160: invokestatic  #108                // Method java/lang/String.valueOf:(I)Ljava/lang/String;
     163: invokevirtual #52                 // Method java/lang/StringBuilder.append:(Ljava/lang/String;)Ljava/lang/StringBuilder;
     166: ldc           #111                // String  frequent renter points
     168: invokevirtual #52                 // Method java/lang/StringBuilder.append:(Ljava/lang/String;)Ljava/lang/StringBuilder;
     171: invokevirtual #58                 // Method java/lang/StringBuilder.toString:()Ljava/lang/String;
     174: astore_2      
     175: aload_2       
     176: areturn       

  public java.lang.String htmlStatement();
    Code:
       0: aload_0       
       1: getfield      #20                 // Field _rentals:Ljava/util/Vector;
       4: invokevirtual #40                 // Method java/util/Vector.elements:()Ljava/util/Enumeration;
       7: astore_1      
       8: new           #44                 // class java/lang/StringBuilder
      11: dup           
      12: ldc           #121                // String Result
      14: invokespecial #48                 // Method java/lang/StringBuilder."<init>":(Ljava/lang/String;)V
      17: aload_0       
      18: invokevirtual #50                 // Method getName:()Ljava/lang/String;
      21: invokevirtual #52                 // Method java/lang/StringBuilder.append:(Ljava/lang/String;)Ljava/lang/StringBuilder;
      24: ldc           #123                // String </EM></H1><P>\n
      26: invokevirtual #52                 // Method java/lang/StringBuilder.append:(Ljava/lang/String;)Ljava/lang/StringBuilder;
      29: invokevirtual #58                 // Method java/lang/StringBuilder.toString:()Ljava/lang/String;
      32: astore_2      
      33: goto          86
      36: aload_1       
      37: invokeinterface #61,  1           // InterfaceMethod java/util/Enumeration.nextElement:()Ljava/lang/Object;
      42: checkcast     #67                 // class rentalStore/Rental
      45: astore_3      
      46: new           #44                 // class java/lang/StringBuilder
      49: dup           
      50: aload_2       
      51: invokestatic  #69                 // Method java/lang/String.valueOf:(Ljava/lang/Object;)Ljava/lang/String;
      54: invokespecial #48                 // Method java/lang/StringBuilder."<init>":(Ljava/lang/String;)V
      57: aload_3       
      58: invokevirtual #77                 // Method rentalStore/Rental.getMovie:()LrentalStore/Movie;
      61: invokevirtual #81                 // Method rentalStore/Movie.getTitle:()Ljava/lang/String;
      64: invokevirtual #52                 // Method java/lang/StringBuilder.append:(Ljava/lang/String;)Ljava/lang/StringBuilder;
      67: aload_3       
      68: invokevirtual #86                 // Method rentalStore/Rental.getCharge:()D
      71: invokestatic  #90                 // Method java/lang/String.valueOf:(D)Ljava/lang/String;
      74: invokevirtual #52                 // Method java/lang/StringBuilder.append:(Ljava/lang/String;)Ljava/lang/StringBuilder;
      77: ldc           #125                // String <BR>\n
      79: invokevirtual #52                 // Method java/lang/StringBuilder.append:(Ljava/lang/String;)Ljava/lang/StringBuilder;
      82: invokevirtual #58                 // Method java/lang/StringBuilder.toString:()Ljava/lang/String;
      85: astore_2      
      86: aload_1       
      87: invokeinterface #93,  1           // InterfaceMethod java/util/Enumeration.hasMoreElements:()Z
      92: ifne          36
      95: new           #44                 // class java/lang/StringBuilder
      98: dup           
      99: aload_2       
     100: invokestatic  #69                 // Method java/lang/String.valueOf:(Ljava/lang/Object;)Ljava/lang/String;
     103: invokespecial #48                 // Method java/lang/StringBuilder."<init>":(Ljava/lang/String;)V
     106: ldc           #127                // String result2
     108: invokevirtual #52                 // Method java/lang/StringBuilder.append:(Ljava/lang/String;)Ljava/lang/StringBuilder;
     111: aload_0       
     112: invokespecial #99                 // Method getTotalCharge:()D
     115: invokestatic  #90                 // Method java/lang/String.valueOf:(D)Ljava/lang/String;
     118: invokevirtual #52                 // Method java/lang/StringBuilder.append:(Ljava/lang/String;)Ljava/lang/StringBuilder;
     121: ldc           #129                // String </EM><P>\n
     123: invokevirtual #52                 // Method java/lang/StringBuilder.append:(Ljava/lang/String;)Ljava/lang/StringBuilder;
     126: invokevirtual #58                 // Method java/lang/StringBuilder.toString:()Ljava/lang/String;
     129: astore_2      
     130: new           #44                 // class java/lang/StringBuilder
     133: dup           
     134: aload_2       
     135: invokestatic  #69                 // Method java/lang/String.valueOf:(Ljava/lang/Object;)Ljava/lang/String;
     138: invokespecial #48                 // Method java/lang/StringBuilder."<init>":(Ljava/lang/String;)V
     141: ldc           #131                // String result3
     143: invokevirtual #52                 // Method java/lang/StringBuilder.append:(Ljava/lang/String;)Ljava/lang/StringBuilder;
     146: aload_0       
     147: invokespecial #104                // Method getTotalFrequentRenterPoints:()I
     150: invokestatic  #108                // Method java/lang/String.valueOf:(I)Ljava/lang/String;
     153: invokevirtual #52                 // Method java/lang/StringBuilder.append:(Ljava/lang/String;)Ljava/lang/StringBuilder;
     156: invokevirtual #58                 // Method java/lang/StringBuilder.toString:()Ljava/lang/String;
     159: astore_2      
     160: aload_2       
     161: areturn       

  private double getTotalCharge();
    Code:
       0: dconst_0      
       1: dstore_1      
       2: aload_0       
       3: getfield      #20                 // Field _rentals:Ljava/util/Vector;
       6: invokevirtual #40                 // Method java/util/Vector.elements:()Ljava/util/Enumeration;
       9: astore_3      
      10: goto          32
      13: aload_3       
      14: invokeinterface #61,  1           // InterfaceMethod java/util/Enumeration.nextElement:()Ljava/lang/Object;
      19: checkcast     #67                 // class rentalStore/Rental
      22: astore        4
      24: dload_1       
      25: aload         4
      27: invokevirtual #86                 // Method rentalStore/Rental.getCharge:()D
      30: dadd          
      31: dstore_1      
      32: aload_3       
      33: invokeinterface #93,  1           // InterfaceMethod java/util/Enumeration.hasMoreElements:()Z
      38: ifne          13
      41: dload_1       
      42: dreturn       

  private int getTotalFrequentRenterPoints();
    Code:
       0: iconst_0      
       1: istore_1      
       2: aload_0       
       3: getfield      #20                 // Field _rentals:Ljava/util/Vector;
       6: invokevirtual #40                 // Method java/util/Vector.elements:()Ljava/util/Enumeration;
       9: astore_2      
      10: goto          30
      13: aload_2       
      14: invokeinterface #61,  1           // InterfaceMethod java/util/Enumeration.nextElement:()Ljava/lang/Object;
      19: checkcast     #67                 // class rentalStore/Rental
      22: astore_3      
      23: iload_1       
      24: aload_3       
      25: invokevirtual #134                // Method rentalStore/Rental.getFrequentRenterPoints:()I
      28: iadd          
      29: istore_1      
      30: aload_2       
      31: invokeinterface #93,  1           // InterfaceMethod java/util/Enumeration.hasMoreElements:()Z
      36: ifne          13
      39: iload_1       
      40: ireturn       
}
